depyf/VERSION.txt
depyf/__init__.py
depyf/code_transform.py
depyf/decompiler.py
depyf/optimization.py
depyf/utils.py
depyf/explain/__init__.py
depyf/explain/enable_debugging.py
depyf/explain/enhance_logging.py
depyf/explain/global_variables.py
depyf/explain/patched___call__.py
depyf/explain/patched__exec_with_source.py
depyf/explain/patched_boxed_run.py
depyf/explain/patched_lazy_format_graph_code.py
depyf/explain/patched_load_by_key_path.py
depyf/explain/utils.py
depyf-0.18.0.dist-info/LICENSE
depyf-0.18.0.dist-info/METADATA
depyf-0.18.0.dist-info/WHEEL
depyf-0.18.0.dist-info/top_level.txt
depyf-0.18.0.dist-info/RECORD
