Metadata-Version: 2.1
Name: depyf
Version: 0.18.0
Summary: Decompile python functions, from bytecode to source code!
Home-page: https://github.com/thuml/depyf
Author: Kaichao You
Author-email: youkaichao@gmail.com
License: MIT
Requires-Python: >=3.7
License-File: LICENSE
Requires-Dist: astor
Requires-Dist: dill
Provides-Extra: dev
Requires-Dist: pytest ; extra == 'dev'
Requires-Dist: flake8 ; extra == 'dev'
Requires-Dist: autopep8 ; extra == 'dev'
